greenflow_hrp_plugin/__init__.py
greenflow_hrp_plugin/aggregateTimeFeature.py
greenflow_hrp_plugin/bootstrapNode.py
greenflow_hrp_plugin/client.py
greenflow_hrp_plugin/diffNode.py
greenflow_hrp_plugin/distanceNode.py
greenflow_hrp_plugin/featureNode.py
greenflow_hrp_plugin/hierarchicalClusteringNode.py
greenflow_hrp_plugin/hrpWeight.py
greenflow_hrp_plugin/kernels.py
greenflow_hrp_plugin/leverageNode.py
greenflow_hrp_plugin/loadCsvNode.py
greenflow_hrp_plugin/logReturnNode.py
greenflow_hrp_plugin/maxDrawdownNode.py
greenflow_hrp_plugin/mergeNode.py
greenflow_hrp_plugin/nrpWeightNode.py
greenflow_hrp_plugin/performanceMetricNode.py
greenflow_hrp_plugin/portfolioNode.py
greenflow_hrp_plugin/rSquaredNode.py
greenflow_hrp_plugin/rawDataNode.py
greenflow_hrp_plugin/shapSummaryPlotNode.py
greenflow_hrp_plugin/transactionCostNode.py
greenflow_hrp_plugin-0.0.0.dist-info/LICENSE
greenflow_hrp_plugin-0.0.0.dist-info/METADATA
greenflow_hrp_plugin-0.0.0.dist-info/WHEEL
greenflow_hrp_plugin-0.0.0.dist-info/entry_points.txt
greenflow_hrp_plugin-0.0.0.dist-info/top_level.txt
greenflow_hrp_plugin-0.0.0.dist-info/RECORD
